README.txt
bootstrap.py
buildout.cfg
setup.py
docs/HISTORY.txt
docs/INSTALL.txt
docs/LICENSE.BSD
mr/__init__.py
mr.bent.egg-info/PKG-INFO
mr.bent.egg-info/SOURCES.txt
mr.bent.egg-info/dependency_links.txt
mr.bent.egg-info/namespace_packages.txt
mr.bent.egg-info/not-zip-safe
mr.bent.egg-info/requires.txt
mr.bent.egg-info/top_level.txt
mr/bent/README.txt
mr/bent/__init__.py
mr/bent/mavolio.py
mr/bent/monkey.py
mr/bent/plugins.py
mr/bent/utils.py
mr/bent/wrapper.py
mr/bent/tests/__init__.py
mr/bent/tests/mock.py
mr/bent/tests/test_bent.py
mr/bent/tests/test_doctest.py
mr/bent/tests/test_monkey.py
mr/bent/tests/test_utils.py
mr/bent/tests/test_wrapper.py
mr/bent/tests/utils.py