Metadata-Version: 1.0
Name: mr.bent
Version: 1.0a1
Summary: Mr. Bent knows his numbers.
Home-page: http://dev.plone.org/collective/browser/mr.bent
Author: Plone Foundation
Author-email: plone-developers@lists.sourceforge.net
License: BSD
Download-URL: http://cheeseshop.python.org/pypi/mr.bent/
Keywords: statistics profiling
Platform: Any
Classifier: Development Status :: 2 - Pre-Alpha
Classifier: Environment :: Web Environment
Classifier: Intended Audience :: Developers
Classifier: Intended Audience :: System Administrators
Classifier: Intended Audience :: Other Audience
Classifier: License :: OSI Approved :: BSD License
Classifier: Operating System :: OS Independent
Classifier: Programming Language :: Python
Classifier: Topic :: Software Development :: Libraries :: Python Modules
